<?xml version="1.0" encoding="UTF-8"?>
<lom xmlns="http://ltsc.ieee.org/xsd/LOM" xmlns:xsi="http://www.w3.org/2001/XMLSchema-instance" xsi:schemaLocation="http://ltsc.ieee.org/xsd/LOM http://i2geo.net/ontologies/lomschema/lom-i2g.xsd">
  <general>
    <!-- 1: General -->
    <identifier>
      <catalog>i2g</catalog>
      <entry>Coll_yamine.Airedespolygonesreguliers</entry>
    </identifier>
    <title>
      <string language="fr">Aire des polygones réguliers</string>
    </title>
    <language>fr</language>
    <description>
      <string language="fr">Cette activité va permettre à l'élève de ressortir l’expression qui détermine l’aire d’un polygone régulier : coté&lt;strong&gt;apothème&lt;/strong&gt;nombre de côtés/2, en exploitant les propriétés d’un polygone régulier.
Il se rendra compte ensuite que l’aire d’un polygone non régulier ne peut être calculée par une expression généralisée.
Une démonstration va permettre aux élèves de visualiser la dynamique du partage d’un polygone régulier en triangles isocèles, d’où l’élève sera convaincu que l’aire d’un polygone régulier dépend essentiellement de l’aire d’un triangle isocèle.   &lt;p/&gt;</string>
    </description>
    <keyword>
      <string language="fr" />
      <!-- ttac =  -->
    </keyword>
  </general>
  <lifeCycle>
    <version>
      <string language="en">5.01</string>
    </version>
    <status>
      <source>LOMv1.0</source>
      <value>revised</value>
    </status>
    <contribute>
      <role>
        <source>LOMv1.0</source>
        <value>initiator</value>
      </role>
      <entity>BEGIN:VCARD&#xD;
VERSION:4.0&#xD;
FN:Akila Mouhous&#xD;
N:Mouhous;Akila;;;&#xD;
END:VCARD</entity>
      <date>
        <dateTime>2011-10-04T01:40:27.000Z</dateTime>
      </date>
    </contribute>
    <contribute>
      <role>
        <source>LOMv1.0</source>
        <value>editor</value>
      </role>
      <entity>BEGIN:VCARD&#xD;
VERSION:4.0&#xD;
FN:Akila Mouhous&#xD;
N:Mouhous;Akila;;;&#xD;
END:VCARD</entity>
      <date>
        <dateTime>2011-10-04T15:19:33.000Z</dateTime>
      </date>
    </contribute>
  </lifeCycle>
  <technical>
    <format>zip</format>
    <size>33078</size>
    <!-- THINKME: OS requirements? could derive form DGS format, see examples   <requirement>-->
    <location>http://i2geo.net/Coll_yamine/Airedespolygonesreguliers</location>
  </technical>
  <educational>
    <!-- educational annotations from Curriki's ICT activity_lab
    true    true         -->
    <interactivityType>
      <source>LOMv1.0</source>
      <value>active</value>
    </interactivityType>
    <learningResourceType>
      <source>LOMv1.0</source>
      <value>other</value>
    </learningResourceType>
    <!-- i2g-context: as precise as possible but not interoperable
                        <context><source>i2g</source>                <value>http://www.inter2geo.eu/2008/ontology/GeoSkills</value>
            </context>
                                     -->
    <language>fr</language>
  </educational>
  <rights>
    <cost>
      <source>LOMv1.0</source>
      <value>no</value>
    </cost>
    <copyrightAndOtherRestrictions>
      <source>LOMv1.0</source>
      <value>yes</value>
    </copyrightAndOtherRestrictions>
    <description>
      <string language="en">i2geo License (Creative Commons Attributions 3.0)</string>
    </description>
    <!-- <licenseURI>http://creativecommons.org/licenses/by/3.0/</licenseURI> -->
  </rights>
</lom>

